aspaceai/__init__.py
aspaceai/aithemes/__init__.py
aspaceai/aithemes/nlp.py
aspaceai/aithemes/sense.py
aspaceai/aithemes/speech.py
aspaceai/aithemes/vision.py
aspaceai/utility/__init__.py
aspaceai/utility/aspaceconnector.py
aspaceai-1.0.13.dist-info/METADATA
aspaceai-1.0.13.dist-info/WHEEL
aspaceai-1.0.13.dist-info/license.txt
aspaceai-1.0.13.dist-info/top_level.txt
aspaceai-1.0.13.dist-info/RECORD
