Metadata-Version: 2.1
Name: aspaceai
Version: 1.0.13
Summary: Python SDK for the ASpace AI cognitive services
Home-page: https://www.ey.com/en_in/consulting/accelerating-digital-transformation-with-ai
Author: Salil Shekharan
Author-email: salilshekharan@gmail.com
License: UNKNOWN
Platform: UNKNOWN
Classifier: Programming Language :: Python
Classifier: License :: OSI Approved :: MIT License
Classifier: Operating System :: OS Independent
Requires-Python: >=3.7.9
